_pyMCFSimplex.cpython-39-darwin.so
pyMCFSimplex.py
pyMCFSimplex-0.9.4.dist-info/METADATA
pyMCFSimplex-0.9.4.dist-info/WHEEL
pyMCFSimplex-0.9.4.dist-info/top_level.txt
pyMCFSimplex-0.9.4.dist-info/RECORD
