Metadata-Version: 2.1
Name: pyMCFSimplex
Version: 0.9.4
Summary: pyMCFSimplex is a Python Wrapper for MCFSimplex
Home-page: http://www.sommer-forst.de/blog
Author: G#.Blog - Johannes Sommer
Author-email: info@sommer-forst.de
License: LGPL 2.1
Platform: win32
Platform: manylinux1_x86_64
Requires-Dist: numpy
